hsr_getyundata_v1/__init__.py
hsr_getyundata-0.1.2.dist-info/METADATA
hsr_getyundata-0.1.2.dist-info/WHEEL
hsr_getyundata-0.1.2.dist-info/entry_points.txt
hsr_getyundata-0.1.2.dist-info/top_level.txt
hsr_getyundata-0.1.2.dist-info/RECORD
